component_builder/__init__.py
component_builder/__main__.py
component_builder/build.py
component_builder/component.py
component_builder/config.py
component_builder/discover.py
component_builder/envs.py
component_builder/exceptions.py
component_builder/github.py
component_builder/release.py
component_builder/utils.py
component_builder-1.1.2.data/scripts/tag-push
component_builder-1.1.2.dist-info/METADATA
component_builder-1.1.2.dist-info/WHEEL
component_builder-1.1.2.dist-info/entry_points.txt
component_builder-1.1.2.dist-info/top_level.txt
component_builder-1.1.2.dist-info/RECORD
