Metadata-Version: 2.1
Name: component-builder
Version: 1.1.2
Summary: Build runner of components for testing/releasing purposes.
Home-page: UNKNOWN
Author: UNKNOWN
Author-email: UNKNOWN
License: UNKNOWN
Platform: UNKNOWN
Classifier: Development Status :: 4 - Beta
Classifier: Intended Audience :: Developers
Classifier: License :: OSI Approved :: GNU Library or Lesser General Public License (LGPL)
Classifier: Operating System :: MacOS
Classifier: Operating System :: POSIX
Classifier: Programming Language :: Python :: 2.7
Classifier: Programming Language :: Python :: 3.5
Classifier: Topic :: Software Development :: Libraries :: Python Modules
Requires-Dist: bash (>=0.5)
Requires-Dist: docopt
Requires-Dist: github3.py (~=1.0.0)
Requires-Dist: pytz (>=2015.4)
